youtube_comment_export-1.1.2.dist-info/licenses/License
ytComments/__about__.py
ytComments/__init__.py
ytComments/cli.py
ytComments/settingsManager.py
ytComments/youtube.py
ytComments/gui/__init__.py
ytComments/gui/about.py
ytComments/gui/app.py
ytComments/gui/error.py
ytComments/gui/main.py
ytComments/gui/menu.py
ytComments/gui/progressbar.py
ytComments/gui/settings.py
ytComments/gui/update.py
youtube_comment_export-1.1.2.dist-info/METADATA
youtube_comment_export-1.1.2.dist-info/WHEEL
youtube_comment_export-1.1.2.dist-info/entry_points.txt
youtube_comment_export-1.1.2.dist-info/top_level.txt
youtube_comment_export-1.1.2.dist-info/RECORD
