Metadata-Version: 2.4
Name: Youtube-Comment-Export
Version: 1.1.2
Summary: Export a YouTube channel Comments in a nice Excel format.
Home-page: https://github.com/Atem83/Youtube-Comment-Export
Author: Michaël AUGUSTE
License: MIT
Classifier: Operating System :: OS Independent
Classifier: Programming Language :: Python
Classifier: License :: OSI Approved :: MIT License
License-File: License
Requires-Dist: yt_dlp
Requires-Dist: polars
Requires-Dist: xlsxwriter
Requires-Dist: colorama
Requires-Dist: PySide6
Requires-Dist: screeninfo
Requires-Dist: requests
Requires-Dist: packaging
Dynamic: license-file
